Metadata-Version: 1.0
Name: probability-distributions-egv
Version: 1.1
Summary: probability distributions_egv
Home-page: UNKNOWN
Author: UNKNOWN
Author-email: UNKNOWN
License: UNKNOWN
Platform: UNKNOWN
